{"Location":{"0":"Algeria","1":"Angola","2":"Benin","3":"Botswana","4":"Burkina Faso","5":"Burundi","6":"Cabo Verde","7":"Cameroon","8":"Central African Republic","9":"Chad","10":"Comoros","11":"Congo","12":"C\u00f4te d'Ivoire","13":"Democratic Republic of the Congo","14":"Djibouti","15":"Egypt","16":"Equatorial Guinea","17":"Eritrea","18":"Eswatini","19":"Ethiopia","20":"Gabon","21":"Gambia","22":"Ghana","23":"Guinea","24":"Guinea-Bissau","25":"Kenya","26":"Lesotho","27":"Liberia","28":"Libya","29":"Madagascar","30":"Malawi","31":"Mali","32":"Mauritania","33":"Mauritius","34":"Morocco","35":"Mozambique","36":"Namibia","37":"Niger","38":"Nigeria","39":"Rwanda","40":"Sao Tome and Principe","41":"Senegal","42":"Seychelles","43":"Sierra Leone","44":"Somalia","45":"South Africa","46":"South Sudan","47":"Sudan","48":"Togo","49":"Tunisia","50":"Uganda","51":"United Republic of Tanzania","52":"Zambia","53":"Zimbabwe"},"2010 - 2015":{"0":31.49,"1":28.74,"2":29.0,"3":28.07,"4":29.38,"5":31.06,"6":27.58,"7":28.72,"8":28.92,"9":28.57,"10":30.14,"11":29.04,"12":29.08,"13":29.57,"14":32.08,"15":27.6,"16":28.34,"17":29.67,"18":27.99,"19":29.81,"20":28.98,"21":30.17,"22":29.88,"23":29.07,"24":29.67,"25":28.84,"26":28.17,"27":28.68,"28":32.85,"29":28.11,"30":28.34,"31":29.04,"32":30.51,"33":27.82,"34":30.29,"35":28.74,"36":29.0,"37":29.07,"38":29.8,"39":30.38,"40":28.68,"41":30.15,"42":27.43,"43":29.04,"44":30.13,"45":27.8,"46":29.78,"47":29.78,"48":29.18,"49":31.07,"50":29.04,"51":29.04,"52":28.75,"53":27.96},"2015 - 2020":{"0":31.66,"1":28.79,"2":28.86,"3":28.06,"4":29.23,"5":31.06,"6":27.38,"7":28.91,"8":28.92,"9":28.76,"10":30.04,"11":29.01,"12":29.08,"13":29.36,"14":32.16,"15":27.6,"16":28.06,"17":29.54,"18":27.7,"19":29.73,"20":29.21,"21":30.4,"22":29.79,"23":29.1,"24":29.56,"25":28.7,"26":27.91,"27":28.45,"28":32.82,"29":27.96,"30":28.04,"31":29.0,"32":30.49,"33":28.14,"34":30.29,"35":28.6,"36":29.01,"37":29.06,"38":29.81,"39":30.32,"40":28.81,"41":30.26,"42":27.51,"43":28.73,"44":29.68,"45":27.72,"46":29.57,"47":30.02,"48":28.93,"49":31.04,"50":28.84,"51":28.76,"52":28.76,"53":28.2}}